[{"place_id": 367200750, "licence": "Data \u00a9 OpenStreetMap contributors, ODbL 1.0. http://osm.org/copyright", "osm_type": "way", "osm_id": 344093468, "lat": "-6.1238179", "lon": "106.7532547", "class": "highway", "type": "secondary", "place_rank": 26, "importance": 0.10000999999999993, "addresstype": "road", "name": "Jalan Pantai Indah Timur", "display_name": "Jalan Pantai Indah Timur, RW 06, Kapuk Muara, Penjaringan, North Jakarta, Special Region of Jakarta, Java, 14460, Indonesia", "boundingbox": ["-6.1244513", "-6.1230816", "106.7531225", "106.7534706"]}]